Workbook

Sheet EXPENSES
A1: DATE | B1: DAY | C1: MONTH | D1: YEAR | E1: CATEGORY | F1: EXPENSE DETAIL | G1: AMOUNT(₹) | H1: PAYMENT METHOD | J1: CATEGORY | K1: TOTAL AMOUNT
A2: 45658 | B2: =DAY(A2) -> 1 | C2: =MONTH(A2) -> 1 | D2: =YEAR(A2) -> 2025 | E2: FOOD | F2: LUNCH | G2: 230 | H2: UPI | J2: FOOD | K2: =SUMIF(E:E,J2,G:G) -> 4550
A3: 45659 | B3: =DAY(A3) -> 2 | C3: =MONTH(A3) -> 1 | D3: =YEAR(A3) -> 2025 | E3: TRAVEL | F3: BUSS PASS | G3: 1110 | H3: CARD | J3: TRAVEL | K3: =SUMIF(E:E,J3,G:G) -> 4580
A4: 45691 | B4: =DAY(A4) -> 3 | C4: =MONTH(A4) -> 2 | D4: =YEAR(A4) -> 2025 | E4: FEES | F4: EXAM FEES | G4: 330 | H4: CASH | J4: FEES | K4: =SUMIF(E:E,J4,G:G) -> 7613.3333
A5: 45720 | B5: =DAY(A5) -> 4 | C5: =MONTH(A5) -> 3 | D5: =YEAR(A5) -> 2025 | E5: SHOPPING | F5: SHOES | G5: 656.66667 | H5: CARD | J5: SHOPPING | K5: =SUMIF(E:E,J5,G:G) -> 3870
A6: 45658 | B6: =DAY(A6) -> 1 | C6: =MONTH(A6) -> 1 | D6: =YEAR(A6) -> 2025 | E6: OTHER | F6: MOBILE RECHARGE | G6: 2706.6667 | H6: CARD | J6: OTHER | K6: =SUMIF(E:E,J6,G:G) -> 5020
A7: 45659 | B7: =DAY(A7) -> 2 | C7: =MONTH(A7) -> 1 | D7: =YEAR(A7) -> 2025 | E7: FEES | F7: TUITION FEES | G7: 756.66667 | H7: UPI
A8: 45691 | B8: =DAY(A8) -> 3 | C8: =MONTH(A8) -> 2 | D8: =YEAR(A8) -> 2025 | E8: FOOD | F8: SWEETS | G8: 806.66667 | H8: UPI
A9: 45720 | B9: =DAY(A9) -> 4 | C9: =MONTH(A9) -> 3 | D9: =YEAR(A9) -> 2025 | E9: TRAVEL | F9: FLIGHT TICKET | G9: 856.66667 | H9: CARD
A10: 45658 | B10: =DAY(A10) -> 1 | C10: =MONTH(A10) -> 1 | D10: =YEAR(A10) -> 2025 | E10: FEES | F10: TRAINING FEES | G10: 2906.6667 | H10: CASH
A11: 45659 | B11: =DAY(A11) -> 2 | C11: =MONTH(A11) -> 1 | D11: =YEAR(A11) -> 2025 | E11: SHOPPING | F11: CLOTHES | G11: 956.66667 | H11: CARD
A12: 45691 | B12: =DAY(A12) -> 3 | C12: =MONTH(A12) -> 2 | D12: =YEAR(A12) -> 2025 | E12: OTHER | F12: ELECRICITY BILL | G12: 1006.6667 | H12: CARD
A13: 45720 | B13: =DAY(A13) -> 4 | C13: =MONTH(A13) -> 3 | D13: =YEAR(A13) -> 2025 | E13: FEES | F13: HOSTEL FEES | G13: 1056.6667 | H13: UPI
A14: 45658 | B14: =DAY(A14) -> 1 | C14: =MONTH(A14) -> 1 | D14: =YEAR(A14) -> 2025 | E14: FOOD | F14: LUNCH | G14: 1106.6667 | H14: UPI
A15: 45659 | B15: =DAY(A15) -> 2 | C15: =MONTH(A15) -> 1 | D15: =YEAR(A15) -> 2025 | E15: TRAVEL | F15: TRAIN TICKET | G15: 1156.6667 | H15: CARD
A16: 45691 | B16: =DAY(A16) -> 3 | C16: =MONTH(A16) -> 2 | D16: =YEAR(A16) -> 2025 | E16: FEES | F16: UNIFORM FEES | G16: 1206.6667 | H16: CASH
A17: 45720 | B17: =DAY(A17) -> 4 | C17: =MONTH(A17) -> 3 | D17: =YEAR(A17) -> 2025 | E17: SHOPPING | F17: SHOCKS | G17: 2256.6667 | H17: CARD
A18: 45658 | B18: =DAY(A18) -> 1 | C18: =MONTH(A18) -> 1 | D18: =YEAR(A18) -> 2025 | E18: OTHER | F18: TV RECHARGE | G18: 1306.6667 | H18: CARD
... A21: 45720 | B21: =DAY(A21) -> 4 | C21: =MONTH(A21) -> 3 | D21: =YEAR(A21) -> 2025 | E21: TRAVEL | F21: SHIP TICKET | G21: 1456.6667 | H21: CARD

Sheet BUDGET
A1: CATEGORY | B1: BUDGET | C1: ACTUAL | D1: DIFFERENCE
A2: FOOD | B2: 3500 | C2: =SUMIF(EXPENSES!E:E,A2,EXPENSES!G:G) -> 4550 | D2: =B2-C2 -> -1050
A3: TRAVEL | B3: 2500 | C3: =SUMIF(EXPENSES!E:E,A3,EXPENSES!G:G) -> 4580 | D3: =B3-C3 -> -2080
A4: FEES | B4: 5000 | C4: =SUMIF(EXPENSES!E:E,A4,EXPENSES!G:G) -> 7613.3333 | D4: =B4-C4 -> -2613.3333
A5: SHOPPING | B5: 4500 | C5: =SUMIF(EXPENSES!E:E,A5,EXPENSES!G:G) -> 3870 | D5: =B5-C5 -> 630
A6: OTHER | B6: 2000 | C6: =SUMIF(EXPENSES!E:E,A6,EXPENSES!G:G) -> 5020 | D6: =B6-C6 -> -3020

Sheet CHARTS
